tcppinglib/__init__.py
tcppinglib/cli.py
tcppinglib/exceptions.py
tcppinglib/models.py
tcppinglib/tcp_multiping.py
tcppinglib/tcp_ping.py
tcppinglib/tcp_sockets.py
tcppinglib/utils.py
tcppinglib-2.0.5.dist-info/licenses/LICENSE
tcppinglib-2.0.5.dist-info/METADATA
tcppinglib-2.0.5.dist-info/WHEEL
tcppinglib-2.0.5.dist-info/entry_points.txt
tcppinglib-2.0.5.dist-info/top_level.txt
tcppinglib-2.0.5.dist-info/RECORD
