Metadata-Version: 2.4
Name: tcppinglib
Version: 2.0.5
Summary: An Easy Way to Measure the Connectivity and Latency with TCP Ping
Author-email: Engin EKEN <e.eken@outlook.com>
License:                     GNU GENERAL PUBLIC LICENSE
Project-URL: Homepage, https://github.com/EnginEken/tcppinglib
Project-URL: Issues, https://github.com/EnginEken/tcppinglib/issues
Keywords: tcp,tcpsockets,tcpping,multitcpping,async,asyncio,ipv4,ipv6,python,python3
Classifier: Development Status :: 5 - Production/Stable
Classifier: Intended Audience :: Developers
Classifier: License :: OSI Approved :: GNU Lesser General Public License v3 or later (LGPLv3+)
Classifier: Operating System :: OS Independent
Classifier: Programming Language :: Python
Classifier: Programming Language :: Python :: 3
Classifier: Programming Language :: Python :: 3 :: Only
Classifier: Programming Language :: Python :: 3.7
Classifier: Programming Language :: Python :: 3.8
Classifier: Programming Language :: Python :: 3.9
Classifier: Programming Language :: Python :: 3.10
Classifier: Topic :: Software Development :: Libraries
Classifier: Topic :: Software Development :: Libraries :: Python Modules
Requires-Python: >=3.7
License-File: LICENSE
Dynamic: license-file
